findora_toolbox/__init__.py
findora_toolbox/app.py
findora_toolbox/config.py
findora_toolbox/library.py
findora_toolbox/test-stats.py
findora_toolbox-1.1.2.dist-info/LICENSE
findora_toolbox-1.1.2.dist-info/METADATA
findora_toolbox-1.1.2.dist-info/WHEEL
findora_toolbox-1.1.2.dist-info/top_level.txt
findora_toolbox-1.1.2.dist-info/RECORD
