Metadata-Version: 2.1
Name: findora-toolbox
Version: 1.1.2
Summary: Findora FRA Validator Node Toolbox and Easy Setup
Home-page: https://github.com/easy-node-pro/findora-toolbox
Author: EasyNode.PRO
Author-email: support@easynode.pro
Project-URL: Bug Tracker, https://github.com/easy-node-pro/findora-toolbox/issues
Project-URL: repository, https://github.com/easy-node-pro/findora-toolbox
Classifier: Programming Language :: Python :: 3
Classifier: License :: OSI Approved :: MIT License
Classifier: Operating System :: OS Independent
License-File: LICENSE
